README.rst
setup.cfg
setup.py
vecvis/__init__.py
vecvis.egg-info/PKG-INFO
vecvis.egg-info/SOURCES.txt
vecvis.egg-info/dependency_links.txt
vecvis.egg-info/top_level.txt
vecvis/mvp/__init__.py
vecvis/mvp/model.py
vecvis/mvp/presenter.py
vecvis/mvp/view.py
vecvis/observable/__init__.py
vecvis/observable/obserable_set.py
vecvis/observable/observable_bool.py
vecvis/observable/observable_number.py
vecvis/observable/observable_ordered_list.py
vecvis/observable/observable_point.py
vecvis/observable/observable_string.py
vecvis/observable/observable_tuple.py
vecvis/star_chart/__init__.py
vecvis/star_chart/arrow.py
vecvis/star_chart/axis.py
vecvis/star_chart/filter_widget.py
vecvis/star_chart/marker.py
vecvis/star_chart/polygon.py
vecvis/star_chart/star_chart.py
vecvis/utils/__init__.py
vecvis/utils/dimension_info.py
vecvis/utils/emitter.py
vecvis/utils/kung.py
vecvis/utils/simple_cull.py
vecvis/utils/utils.py
vecvis/utils/vector2.py
vecvis/utils/ui/__init__.py
vecvis/utils/ui/observable_checkbox.py
vecvis/utils/ui/observable_list.py