Metadata-Version: 1.1
Name: vecvis
Version: 1.0
Summary: A module for showing and filtering vectors
Home-page: https://gitlab.fsi.hochschule-trier.de/goertzm/bachelor
Author: Moritz Goertz
Author-email: goertzm@hochschule-trier.de
License: MIT
Keywords: vector visualization starchart pareto filter
Platform: UNKNOWN
Classifier: Development Status :: 4 - Beta
Classifier: License :: OSI Approved :: MIT License
Classifier: Programming Language :: Python :: 3.5
Classifier: Programming Language :: Python :: 3.4
Classifier: Programming Language :: Python :: 3.6
Classifier: Intended Audience :: Education
Classifier: Intended Audience :: Science/Research
Classifier: Natural Language :: English
Classifier: Operating System :: Microsoft :: Windows
Classifier: Operating System :: Unix
